Workbook

Sheet Entreprises
A1: Entreprise | B1: Enseigne / nom commercial | C1: SIREN | D1: Activité (NAF) | E1: Code NAF | F1: Secteur | G1: Effectif local | H1: Effectif entreprise | I1: Catégorie | J1: Forme juridique | K1: Adresse | L1: Code postal | M1: Commune | N1: Distance Rennes (km) | O1: Étab. 10+ dans la zone | P1: Siège | Q1: Email pour candidater | R1: Email RH / recrutement | S1: Email SI / informatique | T1: Email contact général | U1: Page carrières / candidature | V1: Site web | W1: Source des emails | X1: Statut
A2: KEOLIS RENNES | C2: 340035526 | D2: Transports urbains et suburbains de voyageurs | E2: 49.31Z | F2: Transports et entreposage | G2: 1 000-1 999 | H2: 1 000-1 999 | I2: GE | J2: SA | K2: PLAINE DE BAUD RUE JEAN-MARIE HUCHET 35000 RENNES | L2: 35000 | M2: RENNES | N2: 2.7 | O2: 1 | P2: Dans la zone | V2: https://www.star.fr | X2: Site analysé, aucun email publié
A3: ORANGE | B3: CTRE COMMUN D'ETUDES ET DE TELEDIFFUSION | C3: 380129866 | D3: Télécommunications filaires | E3: 61.10Z | F3: Information et communication | G3: 1 000-1 999 | H3: 10 000 et + | I3: GE | J3: SA | K3: 4 RUE DU CLOS COURTEL 35510 CESSON-SEVIGNE | L3: 35510 | M3: CESSON-SEVIGNE | N3: 4.2 | O3: 1 | P3: Hors zone (Issy-Les-Moulineaux) | V3: https://www.orange.com/ | X3: Site analysé, aucun email publié
A4: CAPGEMINI TECHNOLOGY SERVICES | C4: 479766842 | D4: Conseil en systèmes et logiciels informatiques | E4: 62.02A | F4: Information et communication | G4: 1 000-1 999 | H4: 10 000 et + | I4: GE | J4: SAS | K4: LES CHAMPS BLANCS 7 RUE CLAUDE CHAPPE 35510 CESSON-SEVIGNE | L4: 35510 | M4: CESSON-SEVIGNE | N4: 5.1 | O4: 1 | P4: Hors zone (Issy-Les-Moulineaux) | U4: https://www.fr.sogeti.com/carrieres/nous-rejoindre/ | V4: https://www.fr.sogeti.com | X4: Formulaire / site carrières (pas d'email publié)
A5: STELLANTIS AUTO SAS | C5: 542065479 | D5: Construction de véhicules automobiles | E5: 29.10Z | F5: Industrie manufacturière | G5: 1 000-1 999 | H5: 10 000 et + | I5: GE | J5: SAS | K5: USINE LA JANAIS LA JANAIS 35131 CHARTRES-DE-BRETAGNE | L5: 35131 | M5: CHARTRES-DE-BRETAGNE | N5: 6.2 | O5: 1 | P5: Hors zone (Poissy) | X5: Recherché, aucun site trouvé
A6: INNOVAL (URCEO) | C6: 305321929 | D6: Activités de soutien à la production animale | E6: 01.62Z | F6: Agriculture, sylviculture et pêche | G6: 1 000-1 999 | H6: 1 000-1 999 | J6: Coopérative agricole | K6: CS 80038 RUE ERIC TABARLY 35530 NOYAL-SUR-VILAINE | L6: 35530 | M6: NOYAL-SUR-VILAINE | N6: 10.4 | O6: 1 | P6: Dans la zone | X6: Recherché, aucun site trouvé
A7: BRIDOR | C7: 491668893 | D7: Fabrication industrielle de pain et de pâtisserie fraîche | E7: 10.71A | F7: Industrie manufacturière | G7: 1 000-1 999 | H7: 1 000-1 999 | I7: GE | J7: SAS | K7: ZA D'OLIVET 35530 SERVON-SUR-VILAINE | L7: 35530 | M7: SERVON-SUR-VILAINE | N7: 16.5 | O7: 1 | P7: Hors zone (Paris) | X7: Recherché, aucun site trouvé
A8: FONDAT REGION OUEST LIGUE CANCER | C8: 777739160 | D8: Activités hospitalières | E8: 86.10Z | F8: Santé humaine et action sociale | G8: 500-999 | H8: 500-999 | I8: ETI | J8: Fondation | K8: PONCHAILLOU AV BATAILLE FLANDRES DUNKERQUE 35000 RENNES | L8: 35000 | M8: RENNES | N8: 1.6 | O8: 1 | P8: Dans la zone | Q8: communication@rennes.unicancer.fr | T8: communication@rennes.unicancer.fr | U8: https://www.centre-eugene-marquis.fr/professionnels-de-sante/recrutement/ | V8: https://www.centre-eugene-marquis.fr | W8: https://www.centre-eugene-marquis.fr/ | X8: Email de contact général trouvé
A9: CLINIQUE MUTUALISTE DE LA SAGESSE | C9: 775591076 | D9: Activités hospitalières | E9: 86.10Z | F9: Santé humaine et action sociale | G9: 500-999 | H9: 500-999 | I9: ETI | J9: Mutuelle | K9: 4 PLACE SAINT-GUENOLE 35000 RENNES | L9: 35000 | M9: RENNES | N9: 2.7 | O9: 1 | P9: Dans la zone | Q9: accueil@lasagesse.fr | T9: accueil@lasagesse.fr | V9: http://clinique-rennes.fr/ | W9: https://data.rennesmetropole.fr/explore/dataset/sites_organismes_organismes/ | X9: Email de contact général trouvé
A10: LEGENDRE ILE DE FRANCE | C10: 399394204 | D10: Activités des sièges sociaux | E10: 70.10Z | F10: Construction | G10: 500-999 (estim.) | H10: 500-999 | I10: ETI | J10: SAS | K10: 5 RUE LOUIS-JACQUES DAGUERRE 35136 SAINT-JACQUES-DE-LA-LANDE | L10: 35136 | M10: SAINT-JACQUES-DE-LA-LANDE | N10: 2.9 | O10: 1 | P10: Dans la zone | Q10: communication@groupe-legendre.com | T10: communication@groupe-legendre.com | U10: https://careers.groupe-legendre.com/fr | V10: https://www.groupe-legendre.com/ | W10: https://www.groupe-legendre.com/mentions-legales/ | X10: Email de contact général trouvé
A11: HOSPITALITE SAINT THOMAS DE VILLENEUVE (HSTV) | B11: POLYCLINIQUE SAINT LAURENT | C11: 777380783 | D11: Activités hospitalières | E11: 86.10Z | F11: Santé humaine et action sociale | G11: 500-999 | H11: 2 000-4 999 | I11: ETI | J11: Association | K11: CS10610 320 AVENUE GENERAL GEORGE S. PATTON 35700 RENNES | L11: 35700 | M11: RENNES | N11: 3.4 | O11: 4 | P11: Hors zone (Lamballe-Armor) | Q11: contact@polyclinique-saint-laurent.fr | T11: contact@polyclinique-saint-laurent.fr | V11: https://www.polyclinique-saint-laurent.fr/ | W11: https://www.polyclinique-saint-laurent.fr/mentions-legales | X11: Email de contact général trouvé
A12: CENTRE HOSPITALIER PRIVE SAINT GREGOIRE | B12: VIVALTO SANTE LES HOPITAUX PRIVES RENNAIS | C12: 699201323 | D12: Activités hospitalières | E12: 86.10Z | F12: Santé humaine et action sociale | G12: 500-999 | H12: 500-999 | I12: GE | J12: SAS | K12: CS 56816 6 BOULEVARD DE LA BOUTIERE 35760 SAINT-GREGOIRE | L12: 35760 | M12: SAINT-GREGOIRE | N12: 3.7 | O12: 1 | P12: Dans la zone | Q12: stg.contact@vivalto-sante.com | T12: stg.contact@vivalto-sante.com | U12: https://chpsaintgregoire.mstaff.co/offers?type=default | V12: https://www.vivalto-sante.fr/hopitaux-prives-rennais-saint-gregoire/ | W12: https://www.vivalto-sante.fr/hopitaux-prives-rennais-saint-gregoire/mentions-legales | X12: Email de contact général trouvé
A13: CARSAT BRETAGNE | C13: 777749326 | D13: Activités générales de sécurité sociale | E13: 84.30A | F13: Administration publique | G13: 500-999 | H13: 500-999 | I13: ETI | J13: Organisme de sécurité sociale | K13: 236 RUE DE CHATEAUGIRON 35000 RENNES | L13: 35000 | M13: RENNES | N13: 3.7 | O13: 2 | P13: Dans la zone | Q13: drp.formation@carsat-bretagne.fr | T13: drp.formation@carsat-bretagne.fr | W13: https://www.formation.gref-bretagne.com/ (fiche organisme GREF Bretagne) | X13: Email de contact général trouvé
A14: SOCIETE POUR L'INFORMATIQUE INDUSTRIELLE (SII) | C14: 315000943 | D14: Conseil en systèmes et logiciels informatiques | E14: 62.02A | F14: Information et communication | G14: 500-999 | H14: 2 000-4 999 | I14: GE | J14: SA | K14: 3 B AVENUE DE BELLE FONTAINE 35510 CESSON-SEVIGNE | L14: 35510 | M14: CESSON-SEVIGNE | N14: 4.5 | O14: 1 | P14: Hors zone (Paris) | V14: http://www.groupe-sii.com/ | X14: Site analysé, aucun email publié
A15: OBERTHUR FIDUCIAIRE SAS | C15: 803311372 | D15: Autre imprimerie (labeur) | E15: 18.12Z | F15: Industrie manufacturière | G15: 500-999 | H15: 500-999 | I15: ETI | J15: SAS | K15: 20 RUE DU BREIL 35135 CHANTEPIE | L15: 35135 | M15: CHANTEPIE | N15: 4.5 | O15: 1 | P15: Hors zone (Paris) | Q15: job@fcof.com | R15: job@fcof.com | U15: https://www.oberthur-fiduciaire.com/carrieres/ | V15: https://www.oberthur-fiduciaire.com/ | W15: https://www.oberthur-fiduciaire.com/carrieres/ | X15: Email RH / recrutement trouvé
A16: ORANGE BUSINESS SERVICES | C16: 345039416 | D16: Conseil en systèmes et logiciels informatiques | E16: 62.02A | F16: Information et communication | G16: 500-999 | H16: 5 000-9 999 | I16: GE | J16: SA | K16: 9 RUE DU CHENE GERMAIN 35510 CESSON-SEVIGNE | L16: 35510 | M16: CESSON-SEVIGNE | N16: 4.6 | O16: 2 | P16: Hors zone (Saint-Denis) | X16: Recherché, aucun site trouvé
A17: ATALIAN PROPRETE | C17: 399506641 | D17: Nettoyage courant des bâtiments | E17: 81.21Z | F17: Services administratifs et de soutien | G17: 500-999 | H17: 10 000 et + | I17: GE | J17: SAS | K17: ZAC DE LA RIGOURDIERE 28 RUE DE LA RIGOURDIERE 35510 CESSON-SEVIGNE | L17: 35510 | M17: CESSON-SEVIGNE | N17: 6.8 | O17: 1 | P17: Hors zone (Paris) | U17: https://atalian.com/nos-offres-demploi/ | V17: https://atalian.com/ | X17: Formulaire / site carrières (pas d'email publié)
A18: NET PLUS | C18: 412766206 | D18: Nettoyage courant des bâtiments | E18: 81.21Z | F18: Services administratifs et de soutien | G18: 500-999 | H18: 1 000-1 999 | I18: GE | J18: SAS | K18: RUE DE LA RIGOURDIERE 35510 CESSON-SEVIGNE | L18: 35510 | M18: CESSON-SEVIGNE | N18: 7.7 | O18: 1 | P18: Dans la zone | Q18: contact@net-plus.fr | T18: contact@net-plus.fr | U18: https://net-plus.nous-recrutons.fr/ | V18: https://www.net-plus.fr/ | W18: https://www.net-plus.fr/contact-entreprise-nettoyage/ | X18: Email de contact général trouvé
A19: M-EXTEND FRANCE (MANIP') | C19: 639200260 | D19: Fabrication de matériel de levage et de manutention | E19: 28.22Z | F19: Industrie manufacturière | G19: 500-999 | H19: 500-999 | I19: ETI | J19: SAS | K19: 19 RUE DE RENNES 35690 ACIGNE | L19: 35690 | M19: ACIGNE | N19: 10.3 | O19: 1 | P19: Dans la zone | X19: Recherché, aucun site trouvé
A20: CANON BRETAGNE | C20: 327991774 | D20: Fabrication de machines et d'équipements de bureau (à l'exception des ordinateurs et équipements périphériques) | E20: 28.23Z | F20: Industrie manufacturière | G20: 500-999 | H20: 500-999 | I20: ETI | J20: SAS | K20: LA LANDE DE BEAUGE 35340 LIFFRE | L20: 35340 | M20: LIFFRE | N20: 18.5 | O20: 1 | P20: Dans la zone | Q20: info@cb.canon.fr | T20: info@cb.canon.fr | U20: https://www.canon-bretagne.fr/recrutement/ | V20: https://www.canon-bretagne.fr | W20: https://www.canon-bretagne.fr/mentions-legales/ | X20: Email de contact général trouvé
A21: SANDEN MANUFACTURING EUROPE | C21: 400752028 | D21: Fabrication d'autres pompes et compresseurs | E21: 28.13Z | F21: Industrie manufacturière | G21: 500-999 | H21: 500-999 | I21: ETI | J21: SAS | K21: LD LE QUILLIOU 35190 TINTENIAC | L21: 35190 | M21: TINTENIAC | N21: 23.2 | O21: 1 | P21: Dans la zone | X21: Recherché, aucun site trouvé
A22: PRESTA BREIZH | C22: 393062963 | D22: Transformation et conservation de la viande de boucherie | E22: 10.11Z | F22: Industrie manufacturière | G22: 500-999 | H22: 500-999 | I22: ETI | J22: SAS | K22: ZA DE LA GAUTRAIS 35360 MONTAUBAN-DE-BRETAGNE | L22: 35360 | M22: MONTAUBAN-DE-BRETAGNE | N22: 27.7 | O22: 1 | P22: Dans la zone | Q22: info@prestabreizh.fr | T22: info@prestabreizh.fr | U22: https://careers.werecruit.io/presta-breizh | V22: https://www.prestabreizh.fr/ | W22: https://www.prestabreizh.fr/ | X22: Email de contact général trouvé
A23: KINOUGARDE | C23: 523371052 | D23: Accueil de jeunes enfants | E23: 88.91A | F23: Santé humaine et action sociale | G23: 250-499 | H23: 10 000 et + | I23: ETI | J23: SAS | K23: 39 BOULEVARD DE LA LIBERTE 35000 RENNES | L23: 35000 | M23: RENNES | N23: 0.4 | O23: 1 | P23: Hors zone (Paris) | X23: Recherché, aucun site trouvé
A24: CAISS PRIMA ASSUR MALADIE ILLE & VILAINE | C24: 777749342 | D24: Activités générales de sécurité sociale | E24: 84.30A | F24: Administration publique | G24: 250-499 | H24: 500-999 | I24: ETI | J24: Organisme de sécurité sociale | K24: 7 COURS DES ALLIES 35000 RENNES | L24: 35000 | M24: RENNES | N24: 0.7 | O24: 7 | P24: Dans la zone | Q24: ces@cpam-rennes.cnamts.fr | T24: ces@cpam-rennes.cnamts.fr | U24: https://careers.werecruit.io/fr/cpam-dille-et-vilaine/offres/candidature-spontanee-d726fa | W24: OpenStreetMap | X24: Email de contact général trouvé
A25: CAISSE D ALLOCATIONS FAMILIALES D ILLE ET VILAINE (CAF 35) | C25: 777749375 | D25: Distribution sociale de revenus | E25: 84.30C | F25: Administration publique | G25: 250-499 | H25: 250-499 | I25: ETI | J25: Organisme de sécurité sociale | K25: COURS DES ALLIES 35000 RENNES | L25: 35000 | M25: RENNES | N25: 0.7 | O25: 4 | P25: Dans la zone | V25: https://www.caf.fr/ | X25: Site analysé, aucun email publié
A26: FONDATION SAINT-HELIER | B26: POLE MEDECINE PHYSIQUE READAPTATION SAINT HELIER | C26: 504545443 | D26: Activités hospitalières | E26: 86.10Z | F26: Santé humaine et action sociale | G26: 250-499 | H26: 500-999 | I26: ETI | J26: Association | K26: 54 RUE SAINT-HELIER 35000 RENNES | L26: 35000 | M26: RENNES | N26: 0.9 | O26: 3 | P26: Hors zone (Saint-Jacut-Les-Pins) | Q26: accueil.residence@pole-sthelier.com | T26: accueil.residence@pole-sthelier.com | U26: https://www.pole-sthelier.fr/professionnel/ | V26: https://www.pole-sthelier.fr/ | W26: https://data.rennesmetropole.fr/explore/dataset/sites_organismes_organismes/ | X26: Email de contact général trouvé
A27: NEOTOA (HABITAT 35) | C27: 347498370 | D27: Location de logements | E27: 68.20A | F27: Activités immobilières | G27: 250-499 | H27: 250-499 | I27: ETI | J27: EPIC / entreprise publique | K27: 41 BOULEVARD DE VERDUN 35000 RENNES | L27: 35000 | M27: RENNES | N27: 1 | O27: 1 | P27: Dans la zone | Q27: contact@neotoa.fr | T27: contact@neotoa.fr | U27: https://www.neotoa.fr/nous-rejoindre/ | V27: https://www.neotoa.fr/ | W27: OpenStreetMap | X27: Email de contact général trouvé
A28: NIJI | C28: 439055278 | D28: Conseil en systèmes et logiciels informatiques | E28: 62.02A | F28: Information et communication | G28: 250-499 | H28: 1 000-1 999 | I28: ETI | J28: SAS | K28: IDENTITY 1 9 RUE DE CHATILLON 35000 RENNES | L28: 35000 | M28: RENNES | N28: 1.1 | O28: 1 | P28: Dans la zone | V28: https://www.niji.fr | X28: Site analysé, aucun email publié
A29: BOUCHERS SERVICES | C29: 317238061 | D29: Transformation et conservation de la viande de boucherie | E29: 10.11Z | F29: Industrie manufacturière | G29: 250-499 | H29: 1 000-1 999 | I29: ETI | J29: SAS | K29: 2 RUE DE LA MABILAIS 35000 RENNES | L29: 35000 | M29: RENNES | N29: 1.2 | O29: 2 | P29: Dans la zone | Q29: recrutement@bouchers-services.com | R29: recrutement@bouchers-services.com | W29: Overture Maps (données ouvertes, fiche lieu « Bouchers Services ») | X29: Email RH / recrutement trouvé
A30: HELLOWORK | C30: 428843130 | D30: Traitement de données, hébergement et activités connexes | E30: 63.11Z | F30: Information et communication | G30: 250-499 | H30: 500-999 | I30: ETI | J30: SAS | K30: 2 RUE DE LA MABILAIS 35000 RENNES | L30: 35000 | M30: RENNES | N30: 1.2 | O30: 1 | P30: Dans la zone | U30: https://carrieres.hellowork-group.com/ | V30: https://www.hellowork-group.com/fr/ | X30: Formulaire / site carrières (pas d'email publié)
A31: OEUVRES AUGUSTINES ST YVES | C31: 302819784 | D31: Activités hospitalières | E31: 86.10Z | F31: Santé humaine et action sociale | G31: 250-499 | H31: 250-499 | I31: PME | J31: Association | K31: 4 RUE ADOLPHE LERAY 35000 RENNES | L31: 35000 | M31: RENNES | N31: 1.7 | O31: 1 | P31: Dans la zone | Q31: contact@clinique-styves.fr | T31: contact@clinique-styves.fr | U31: http://www.clinique-styves.fr/offres-emploi/ | V31: https://www.clinique-styves.fr/ | W31: OpenStreetMap | X31: Email de contact général trouvé
A32: ENEDIS | C32: 444608442 | D32: Distribution d'électricité | E32: 35.13Z | F32: Énergie (électricité, gaz, vapeur) | G32: 250-499 | H32: 10 000 et + | I32: GE | J32: SA | K32: 64 BOULEVARD VOLTAIRE 35000 RENNES | L32: 35000 | M32: RENNES | N32: 1.8 | O32: 1 | P32: Hors zone (Puteaux) | U32: https://www.enedis.fr/hub-carriere | V32: https://www.enedis.fr/ | X32: Formulaire / site carrières (pas d'email publié)
A33: GROUPE RENNES SCHOOL OF BUSINESS (ESC RENNES) | C33: 378327514 | D33: Enseignement supérieur | E33: 85.42Z | F33: Enseignement | G33: 250-499 | H33: 250-499 | I33: ETI | J33: Association | K33: 2 RUE ROBERT D'ARBRISSEL 35000 RENNES | L33: 35000 | M33: RENNES | N33: 2.1 | O33: 2 | P33: Dans la zone | Q33: esc@esc-rennes.fr | T33: esc@esc-rennes.fr | V33: https://www.esc-rennes.fr | W33: https://data.rennesmetropole.fr/explore/dataset/sites_organismes_organismes/ | X33: Email de contact général trouvé
A34: OPH RENNES METROPOLE ARCHIPEL HABITAT | C34: 452200751 | D34: Location de logements | E34: 68.20A | F34: Activités immobilières | G34: 250-499 | H34: 250-499 | I34: ETI | J34: EPIC / entreprise publique | K34: 3 PLACE DE LA COMMUNAUTE 35000 RENNES | L34: 35000 | M34: RENNES | N34: 2.1 | O34: 1 | P34: Dans la zone | Q34: contact@archipel-habitat.fr | T34: contact@archipel-habitat.fr | U34: https://www.archipel-habitat.fr/nous-rejoindre/archipel-habitat-employeur | V34: https://www.archipel-habitat.fr/ | W34: OpenStreetMap | X34: Email de contact général trouvé
A35: HOPITAL A DOMICILE 35 SIEGE ADMINISTRATIF | C35: 450741640 | D35: Activités hospitalières | E35: 86.10Z | F35: Santé humaine et action sociale | G35: 250-499 | H35: 250-499 | I35: PME | J35: Association | K35: 7 RUE JULES MAILLARD DE LA GOURNERIE 35000 RENNES | L35: 35000 | M35: RENNES | N35: 2.5 | O35: 1 | P35: Dans la zone | Q35: admission@had35.fr | T35: admission@had35.fr | U35: https://had35.fr/nous-rejoindre/ | V35: https://had35.fr/ | W35: https://had35.fr/ | X35: Email de contact général trouvé
A36: ESPACIL HABITAT SA D'HABITATIONS A LOYER MODERE | C36: 302494398 | D36: Activités des sièges sociaux | E36: 70.10Z | F36: Activités immobilières | G36: 250-499 | H36: 250-499 | I36: GE | J36: SA | K36: 20 RUE GUY ROPARTZ 35700 RENNES | L36: 35700 | M36: RENNES | N36: 2.7 | O36: 1 | P36: Dans la zone | U36: https://www.espacil.com/espacil/recrutement | V36: https://www.espacil.com/ | X36: Formulaire / site carrières (pas d'email publié)
A37: RENOUEST | B37: LECLERC | C37: 305008476 | D37: Hypermarchés | E37: 47.11F | F37: Commerce, réparation auto/moto | G37: 250-499 | H37: 250-499 | I37: ETI | J37: SAS | K37: CENTRE COMMERCIAL CLEUNAY RUE JULES VALLES 35000 RENNES | L37: 35000 | M37: RENNES | N37: 2.7 | O37: 2 | P37: Dans la zone | V37: https://www.e.leclerc/mag/e-leclerc-cleunay | X37: Site analysé, aucun email publié
A38: AVANSSUR | C38: 378393946 | D38: Activités des agents et courtiers d'assurances | E38: 66.22Z | F38: Activités financières et d'assurance | G38: 250-499 | H38: 500-999 | I38: GE | J38: SA | K38: BATIMENT ALCYONE 1 RUE ANDRE ET YVONNE MEYNIER 35000 RENNES | L38: 35000 | M38: RENNES | N38: 2.8 | O38: 1 | P38: Hors zone (Suresnes) | U38: https://www.direct-assurance.fr/recrutement | V38: http://www.direct-assurance.fr | X38: Formulaire / site carrières (pas d'email publié)
A39: URSSAF BRETAGNE | C39: 753759570 | D39: Activités générales de sécurité sociale | E39: 84.30A | F39: Administration publique | G39: 250-499 | H39: 500-999 | I39: ETI | J39: Organisme de sécurité sociale | K39: PARC ALCYONE-BATIMENT E 1 RUE ANDRE ET YVONNE MEYNIER 35000 RENNES | L39: 35000 | M39: RENNES | N39: 2.8 | O39: 1 | P39: Dans la zone | X39: Recherché, aucun site trouvé
A40: SODIRENNES TPLM | C40: 320292204 | D40: Hypermarchés | E40: 47.11F | F40: Commerce, réparation auto/moto | G40: 250-499 | H40: 250-499 | I40: ETI | J40: SAS | K40: ZONE INDUSTRIELLE RUE DE L'ETANG AU DIABLE 35760 SAINT-GREGOIRE | L40: 35760 | M40: SAINT-GREGOIRE | N40: 3.1 | O40: 2 | P40: Dans la zone | V40: https://www.e.leclerc/mag/e-leclerc-saint-gregoire | X40: Site analysé, aucun email publié
A41: STADE RENNAIS FOOTBALL CLUB (SRFC) | C41: 344366232 | D41: Activités de clubs de sports | E41: 93.12Z | F41: Arts, spectacles et activités récréatives | G41: 250-499 | H41: 250-499 | I41: GE | J41: SA | K41: LA PIVERDIERE CHEMIN DE LA TAUPINAIS 35000 RENNES | L41: 35000 | M41: RENNES | N41: 3.3 | O41: 1 | P41: Dans la zone | Q41: redaction@staderennais.fr | T41: redaction@staderennais.fr | W41: Overture Maps (données ouvertes, fiche lieu « Stade Rennais F.C. ») | X41: Email de contact général trouvé
A42: NEUWERK RENNES | C42: 844843367 | D42: Fabrication d'autres équipements automobiles | E42: 29.32Z | F42: Industrie manufacturière | G42: 250-499 | H42: 250-499 | I42: GE | J42: SAS | K42: 24 RUE NICOLAS-JOSEPH CUGNOT 35000 RENNES | L42: 35000 | M42: RENNES | N42: 3.3 | O42: 1 | P42: Dans la zone | U42: https://www.continental-industry.com/global/en/career | V42: https://www.continental-industry.com/fr | X42: Formulaire / site carrières (pas d'email publié)
A43: GLD SERVICES | C43: 380855486 | D43: Activités des sièges sociaux | E43: 70.10Z | F43: Services administratifs et de soutien | G43: 250-499 | H43: 250-499 | I43: GE | J43: GIE | K43: 52 AVENUE DU CANADA 35200 RENNES | L43: 35200 | M43: RENNES | N43: 3.4 | O43: 1 | P43: Dans la zone | Q43: communication@groupeleduff.com | T43: communication@groupeleduff.com | U43: https://recrutement.groupeleduff.com/en/annonces | V43: https://en.groupeleduff.com/ | W43: https://en.groupeleduff.com/legal-notices | X43: Email de contact général trouvé
A44: SCALIAN DS (SCALIAN DIGITAL SYSTEMS) | C44: 487574394 | D44: Conseil en systèmes et logiciels informatiques | E44: 62.02A | F44: Information et communication | G44: 250-499 | H44: 1 000-1 999 | I44: GE | J44: SAS | K44: ESPACE NOBEL - BATIMENT A 2 RUE ANTOINE BECQUEREL 35000 RENNES | L44: 35000 | M44: RENNES | N44: 3.7 | O44: 1 | P44: Hors zone (Toulouse) | V44: https://www.scalian.com | X44: Site trouvé, pas encore analysé
A45: CLARANET (ARTFUL, CLARANET, CLARANET ARTFUL, TYPHON) | B45: CLARANET ARTFUL CLARANET ARTFUL, TYPHON | C45: 419632286 | D45: Traitement de données, hébergement et activités connexes | E45: 63.11Z | F45: Information et communication | G45: 250-499 | H45: 500-999 | I45: ETI | J45: SAS | K45: 2 RUE DES LANDELLES 35510 CESSON-SEVIGNE | L45: 35510 | M45: CESSON-SEVIGNE | N45: 3.8 | O45: 1 | P45: Dans la zone | X45: Recherché, aucun site trouvé
A46: INETUM | C46: 385365713 | D46: Conseil en systèmes et logiciels informatiques | E46: 62.02A | F46: Information et communication | G46: 250-499 | H46: 5 000-9 999 | I46: GE | J46: SAS | K46: 14 B RUE DU PATIS TATELIN 35700 RENNES | L46: 35700 | M46: RENNES | N46: 3.9 | O46: 1 | P46: Hors zone (Saint-Ouen-Sur-Seine) | U46: https://www.inetum.com/global/en/careers/jobs.html | V46: https://www.inetum.com/ | X46: Formulaire / site carrières (pas d'email publié)
A47: ASTEK FRANCE | C47: 439752817 | D47: Conseil en systèmes et logiciels informatiques | E47: 62.02A | F47: Information et communication | G47: 250-499 | H47: 2 000-4 999 | I47: ETI | J47: SAS | K47: 14 RUE DU PATIS TATELIN 35700 RENNES | L47: 35700 | M47: RENNES | N47: 3.9 | O47: 1 | P47: Hors zone (Courbevoie) | X47: Recherché, aucun site trouvé
A48: STEF TRANSPORT RENNES | C48: 490675022 | D48: Transports routiers de fret interurbains | E48: 49.41A | F48: Transports et entreposage | G48: 250-499 | H48: 250-499 | I48: GE | J48: SAS | K48: ZI OUEST 6 RUE DU LT COL DUBOIS 35000 RENNES | L48: 35000 | M48: RENNES | N48: 4.1 | O48: 1 | P48: Dans la zone | V48: https://stef.com/ | X48: Site analysé, aucun email publié
A49: AFTEC | B49: AFTEC-IHECF-IPAC BACHELOR FACTORY / MBWAY-MY DIGITAL SCHOOL-WIN | C49: 351191119 | D49: Formation continue d'adultes | E49: 85.59A | F49: Enseignement | G49: 250-499 | H49: 500-999 | I49: ETI | J49: SAS | K49: 23 RUE LOUIS KERAUTRET-BOTMEL 35000 RENNES | L49: 35000 | M49: RENNES | N49: 4.2 | O49: 2 | P49: Dans la zone | Q49: rennes@aftec.fr | T49: rennes@aftec.fr | V49: https://www.aftec.fr/ | W49: https://data.rennesmetropole.fr/explore/dataset/sites_organismes_organismes/ | X49: Email de contact général trouvé
A50: NEO SOFT SERVICES (NEO-SOFT SERVICES) | C50: 484348487 | D50: Conseil en systèmes et logiciels informatiques | E50: 62.02A | F50: Information et communication | G50: 250-499 | H50: 1 000-1 999 | I50: ETI | J50: SAS | K50: 13 RUE DU CLOS COURTEL 35510 CESSON-SEVIGNE | L50: 35510 | M50: CESSON-SEVIGNE | N50: 4.2 | O50: 2 | P50: Hors zone (Paris) | X50: Recherché, aucun site trouvé
A51: ONET SERVICES | C51: 067800425 | D51: Nettoyage courant des bâtiments | E51: 81.21Z | F51: Services administratifs et de soutien | G51: 250-499 | H51: 10 000 et + | I51: GE | J51: SAS | K51: ZI SUD EST RUE DE L'OSERAIE 35510 CESSON-SEVIGNE | L51: 35510 | M51: CESSON-SEVIGNE | N51: 4.2 | O51: 1 | P51: Hors zone (Marseille) | U51: https://www.groupeonet.com/nous-rejoindre/ | V51: https://www.groupeonet.com/ | X51: Formulaire / site carrières (pas d'email publié)
A52: HOPITAL PRIVE SEVIGNE | B52: VIVALTO SANTE LES HOPITAUX PRIVES RENNAIS | C52: 310955323 | D52: Activités hospitalières | E52: 86.10Z | F52: Santé humaine et action sociale | G52: 250-499 | H52: 250-499 | I52: GE | J52: SAS | K52: RUE DU CHENE GERMAIN 35510 CESSON-SEVIGNE | L52: 35510 | M52: CESSON-SEVIGNE | N52: 4.4 | O52: 1 | P52: Dans la zone | Q52: hps.contact@vivalto-sante.com | T52: hps.contact@vivalto-sante.com | U52: https://hopitalprivesevigne.mstaff.co/offers | V52: https://www.vivalto-sante.fr/hopitaux-prives-rennais-cesson-sevigne/ | W52: https://www.vivalto-sante.fr/hopitaux-prives-rennais-cesson-sevigne/mentions-legales | X52: Email de contact général trouvé
A53: TESSI - T.G.D. | C53: 393046784 | D53: Traitement de données, hébergement et activités connexes | E53: 63.11Z | F53: Information et communication | G53: 250-499 | H53: 250-499 | I53: ETI | J53: SAS | K53: 9 RUE DES CHARMILLES 35510 CESSON-SEVIGNE | L53: 35510 | M53: CESSON-SEVIGNE | N53: 4.4 | O53: 1 | P53: Dans la zone | X53: Recherché, aucun site trouvé
A54: HOPPEN FRANCE (HOPPEN) | C54: 379065758 | D54: Location et location-bail d'autres biens personnels et domestiques | E54: 77.29Z | F54: Services administratifs et de soutien | G54: 250-499 | H54: 250-499 | I54: ETI | J54: SAS | K54: BATIMENT ENERGIES B2 3 AVENUE DE BELLE FONTAINE 35510 CESSON-SEVIGNE | L54: 35510 | M54: CESSON-SEVIGNE | N54: 4.5 | O54: 1 | P54: Dans la zone | Q54: communication@hoppen.care | T54: communication@hoppen.care | U54: https://macarriere.hoppen.care/ | V54: https://www.hoppen.care/ | W54: https://www.hoppen.care/contactez-nous/ | X54: Email de contact général trouvé
A55: ORANGE CYBERDEFENSE FRANCE | C55: 512664194 | D55: Conseil en systèmes et logiciels informatiques | E55: 62.02A | F55: Information et communication | G55: 250-499 | H55: 1 000-1 999 | I55: GE | J55: SAS | K55: BREHAT BP 91235 9 RUE DU CHENE GERMAIN 35510 CESSON-SEVIGNE | L55: 35510 | M55: CESSON-SEVIGNE | N55: 4.6 | O55: 1 | P55: Hors zone (Nanterre) | V55: https://orangecyberdefense.com/ | X55: Site analysé, aucun email publié
A56: CGI FRANCE | C56: 702042755 | D56: Conseil en systèmes et logiciels informatiques | E56: 62.02A | F56: Information et communication | G56: 250-499 | H56: 10 000 et + | I56: GE | J56: SAS | K56: 19 RUE DU CHENE GERMAIN 35510 CESSON-SEVIGNE | L56: 35510 | M56: CESSON-SEVIGNE | N56: 4.7 | O56: 1 | P56: Hors zone (Puteaux) | U56: https://cgi.njoyn.com/corp/xweb/xweb.asp?CLID=21001&page=joblisting&CountryID=FR&lang=2&CityID=Rennes | V56: https://www.cgi.com/ | X56: Formulaire / site carrières (pas d'email publié)
A57: ADAPEI 35 | B57: UTOPI SAINT JACQUES DE LA LANDE | C57: 775590920 | D57: Aide par le travail | E57: 88.10C | F57: Santé humaine et action sociale | G57: 250-499 | H57: 2 000-4 999 | I57: ETI | J57: Association | K57: 9 BOULEVARD DE LA HAIE DES COGNETS 35136 SAINT-JACQUES-DE-LA-LANDE | L57: 35136 | M57: SAINT-JACQUES-DE-LA-LANDE | N57: 4.7 | O57: 20 | P57: Dans la zone | Q57: cessonsevigne@utopi.bzh | T57: cessonsevigne@utopi.bzh | U57: https://www.adapei35.com/offres-demploi.html | V57: https://utopi.bzh/ | W57: OpenStreetMap | X57: Email de contact général trouvé
A58: SAMSIC II | C58: 428685358 | D58: Nettoyage courant des bâtiments | E58: 81.21Z | F58: Services administratifs et de soutien | G58: 250-499 | H58: 10 000 et + | I58: GE | J58: SAS | K58: FORUM LA ROCADE REZ DE CHAUSSEE GAUCHE 40 RUE DU BIGNON 35510 CESSON-SEVIGNE | L58: 35510 | M58: CESSON-SEVIGNE | N58: 5 | O58: 3 | P58: Hors zone (Cesson-Sevigne) | Q58: contact@samsic-facility.fr | T58: contact@samsic-facility.fr | U58: https://www.samsic-emploi.fr/ | W58: https://www.samsic.fr/mentions-legales/ | X58: Email de contact général trouvé
A59: EXPERIS FRANCE (EXPERIS) | C59: 394026934 | D59: Conseil en systèmes et logiciels informatiques | E59: 62.02A | F59: Information et communication | G59: 250-499 | H59: 2 000-4 999 | I59: GE | J59: SAS | K59: 975 AVENUE DES CHAMPS BLANCS 35510 CESSON-SEVIGNE | L59: 35510 | M59: CESSON-SEVIGNE | N59: 5.1 | O59: 1 | P59: Hors zone (Nantes) | X59: Pas encore recherché
A60: GSF CELTUS | C60: 344483003 | D60: Autres activités de nettoyage des bâtiments et nettoyage industriel | E60: 81.22Z | F60: Services administratifs et de soutien | G60: 250-499 | H60: 2 000-4 999 | I60: GE | J60: SAS | K60: ZA DE MIVOIE RUE EMILE SOUVESTRE 35136 SAINT-JACQUES-DE-LA-LANDE | L60: 35136 | M60: SAINT-JACQUES-DE-LA-LANDE | N60: 5.3 | O60: 4 | P60: Dans la zone | U60: https://www.gsf.fr/recrutement-gsf/offres-demploi-et-alternance-gsf/ | V60: https://www.gsf.fr/ | X60: Formulaire / site carrières (pas d'email publié)
A61: UGECAM BRPL | C61: 428692008 | D61: Activités hospitalières | E61: 86.10Z | F61: Administration publique | G61: 250-499 | H61: 1 000-1 999 | I61: ETI | J61: Organisme de sécurité sociale | K61: 100 101 100 AVENUE ANDRE BONNIN 35135 CHANTEPIE | L61: 35135 | M61: CHANTEPIE | N61: 5.8 | O61: 2 | P61: Hors zone (Saint-Herblain) | Q61: acc.pgr@ugecam.assurance-maladie.fr | T61: acc.pgr@ugecam.assurance-maladie.fr | U61: https://www.groupe-ugecam.fr/les-offres-emploi/ugecam-bretagne-pays-de-la-loire/pole-geriatrique-rennais | V61: https://www.groupe-ugecam.fr/ | W61: https://www.groupe-ugecam.fr/pole-geriatrique-rennais | X61: Email de contact général trouvé
A62: OET (OET AUTOMATION) (OET) | C62: 301897278 | D62: Ingénierie, études techniques | E62: 71.12B | F62: Activités spécialisées, scientifiques et techniques | G62: 250-499 | H62: 250-499 | I62: ETI | J62: SAS | K62: 1 ROUTE DU GACET 35830 BETTON | L62: 35830 | M62: BETTON | N62: 6.1 | O62: 1 | P62: Dans la zone | U62: https://recrutement.altenov.com/fr/oet | X62: Formulaire / site carrières (pas d'email publié)
A63: SAM GES | C63: 385103023 | D63: Activités des sièges sociaux | E63: 70.10Z | F63: Activités spécialisées, scientifiques et techniques | G63: 250-499 | H63: 250-499 | I63: GE | J63: SAS | K63: LA RIGOURDIERE 6 RUE DE CHATILLON 35510 CESSON-SEVIGNE | L63: 35510 | M63: CESSON-SEVIGNE | N63: 7.2 | O63: 1 | P63: Dans la zone | X63: Pas encore recherché
A64: SAMSIC PROPRETE URBAINE | C64: 814632642 | D64: Activités des sièges sociaux | E64: 70.10Z | F64: Eau, assainissement, déchets, dépollution | G64: 250-499 (estim.) | H64: 250-499 | I64: GE | J64: SAS | K64: LA RIGOURDIERE 6 RUE DE CHATILLON 35510 CESSON-SEVIGNE | L64: 35510 | M64: CESSON-SEVIGNE | N64: 7.2 | O64: 1 | P64: Dans la zone | Q64: contact@samsic-facility.fr | T64: contact@samsic-facility.fr | U64: https://www.samsic-emploi.fr/ | W64: https://www.samsic.fr/mentions-legales/ | X64: Email de contact général trouvé
A65: MSA DES PORTES DE BRETAGNE | C65: 521826107 | D65: Activités générales de sécurité sociale | E65: 84.30A | F65: Administration publique | G65: 250-499 | H65: 500-999 | I65: ETI | J65: Organisme de sécurité sociale | K65: LA PORTE DE KER LANN RUE CHARLES COUDE 35170 BRUZ | L65: 35170 | M65: BRUZ | N65: 7.7 | O65: 1 | P65: Dans la zone | Q65: assistanceinternet.blf@portesdebretagne.msa.fr | T65: assistanceinternet.blf@portesdebretagne.msa.fr | U65: https://portesdebretagne.msa.fr/lfp/nos-offres-d-emploi | V65: https://portesdebretagne.msa.fr/ | W65: https://portesdebretagne.msa.fr/ | X65: Email de contact général trouvé
A66: CARREFOUR SUPPLY CHAIN | C66: 428240287 | D66: Commerce de gros (commerce interentreprises) alimentaire non spécialisé | E66: 46.39B | F66: Transports et entreposage | G66: 250-499 | H66: 5 000-9 999 | I66: GE | J66: SAS | K66: LES CORMIERS 35650 LE RHEU | L66: 35650 | M66: LE RHEU | N66: 8.5 | O66: 1 | P66: Hors zone (Mondeville) | X66: Pas encore recherché
A67: AVEM | C67: 330447236 | D67: Réparation d'ordinateurs et d'équipements périphériques | E67: 95.11Z | F67: Autres activités de services | G67: 250-499 | H67: 1 000-1 999 | I67: GE | J67: SAS | K67: 14 RUE LOUIS BLERIOT 35170 BRUZ | L67: 35170 | M67: BRUZ | N67: 8.9 | O67: 1 | P67: Dans la zone | X67: Recherché, aucun site trouvé
A68: LES ROUTIERS BRETONS | C68: 334300720 | D68: Transports routiers de fret interurbains | E68: 49.41A | F68: Transports et entreposage | G68: 250-499 | H68: 250-499 | I68: ETI | J68: SAS | K68: 11 AVENUE LAVOISIER 35170 BRUZ | L68: 35170 | M68: BRUZ | N68: 9.4 | O68: 1 | P68: Dans la zone | X68: Recherché, aucun site trouvé
A69: SOCIETE LAITIERE DE L'HERMITAGE | C69: 403059843 | D69: Fabrication de lait liquide et de produits frais | E69: 10.51A | F69: Industrie manufacturière | G69: 250-499 | H69: 250-499 | I69: GE | J69: SNC | K69: PLACE DE LA GARE 35590 L'HERMITAGE | L69: 35590 | M69: L'HERMITAGE | N69: 10.5 | O69: 1 | P69: Dans la zone | X69: Pas encore recherché
A70: STG FRIGORIFIQUE | C70: 822841938 | D70: Transports routiers de fret interurbains | E70: 49.41A | F70: Transports et entreposage | G70: 250-499 | H70: 250-499 | I70: ETI | J70: SAS | K70: ZONE D'ACTIVITES NOYAL-SUD 1 RUE DE LA RICHARDIERE 35530 NOYAL-SUR-VILAINE | L70: 35530 | M70: NOYAL-SUR-VILAINE | N70: 10.9 | O70: 1 | P70: Dans la zone | U70: https://www.stg.fr/nos-offres/ | V70: https://www.stg.fr/ | X70: Formulaire / site carrières (pas d'email publié)
A71: GAUTIER FRET SOLUTIONS | C71: 842621294 | D71: Transports routiers de fret interurbains | E71: 49.41A | F71: Transports et entreposage | G71: 250-499 | H71: 250-499 | I71: ETI | J71: SAS | K71: ZA NOYAL SUD 9 RUE LEPINE 35530 NOYAL-SUR-VILAINE | L71: 35530 | M71: NOYAL-SUR-VILAINE | N71: 11.3 | O71: 1 | P71: Dans la zone | Q71: contact@gautierfretsolutions.fr | T71: contact@gautierfretsolutions.fr | U71: https://gautierfretsolutions.fr/rejoignez-nous/ | V71: https://gautierfretsolutions.fr/ | W71: https://gautierfretsolutions.fr/ | X71: Email de contact général trouvé
A72: OLGA | C72: 709200307 | D72: Fabrication de lait liquide et de produits frais | E72: 10.51A | F72: Industrie manufacturière | G72: 250-499 | H72: 500-999 | I72: ETI | J72: SAS | K72: 2 RUE JULIEN NEVEU 35530 NOYAL-SUR-VILAINE | L72: 35530 | M72: NOYAL-SUR-VILAINE | N72: 11.4 | O72: 4 | P72: Dans la zone | Q72: magasin@avec-olga.com | T72: magasin@avec-olga.com | V72: https://www.triballat-noyal.com/ | W72: Overture Maps (données ouvertes, fiche lieu « Magasin Chez Olga ») | X72: Email de contact général trouvé
A73: CASTELDIS | C73: 451762892 | D73: Hypermarchés | E73: 47.11F | F73: Commerce, réparation auto/moto | G73: 250-499 | H73: 250-499 | I73: ETI | J73: SAS | K73: 2 RUE DES COMPTOIRS 35410 CHATEAUGIRON | L73: 35410 | M73: CHATEAUGIRON | N73: 14.4 | O73: 1 | P73: Dans la zone | X73: Recherché, aucun site trouvé
A74: NGE FONDATIONS | C74: 348099987 | D74: Travaux de terrassement courants et travaux préparatoires | E74: 43.12A | F74: Construction | G74: 250-499 | H74: 500-999 | I74: GE | J74: SAS | K74: PA PORTES DE BRETAGNE 14 RUE DES FRERES LUMIERE 35530 SERVON-SUR-VILAINE | L74: 35530 | M74: SERVON-SUR-VILAINE | N74: 16.5 | O74: 1 | P74: Hors zone (Saint-Priest) | X74: Pas encore recherché
A75: GUIDIS SA | C75: 327641767 | D75: Supermarchés | E75: 47.11D | F75: Commerce, réparation auto/moto | G75: 250-499 | H75: 250-499 | I75: PME | J75: SAS | K75: ZA VALONIA 11 RUE LOUIS AMPERE 35580 GUICHEN | L75: 35580 | M75: GUICHEN | N75: 17.7 | O75: 1 | P75: Dans la zone | Q75: hyperu.guichen@systeme-u.fr | T75: hyperu.guichen@systeme-u.fr | W75: https://www.guichenpontrean.fr/contacts/hyper-u/ | X75: Email de contact général trouvé
A76: TENDRIADE | B76: TENDRIADE CHATEAUBOURG | C76: 396020232 | D76: Transformation et conservation de la viande de boucherie | E76: 10.11Z | F76: Industrie manufacturière | G76: 250-499 | H76: 500-999 | I76: ETI | J76: SAS | K76: 22 RUE JOLIOT CURIE 35220 CHATEAUBOURG | L76: 35220 | M76: CHATEAUBOURG | N76: 19.6 | O76: 3 | P76: Dans la zone | Q76: tendriade@tendriade.fr | T76: tendriade@tendriade.fr | U76: https://www.vandriegroup.com/en/careers-at-vandrie-group | V76: https://www.vandriegroup.com/ | W76: https://www.vandriegroup.com/en/our-chain/veal-processing/tendriade | X76: Email de contact général trouvé
A77: COOPERL ARC ATLANTIQUE | C77: 383986874 | D77: Transformation et conservation de la viande de boucherie | E77: 10.11Z | F77: Industrie manufacturière | G77: 250-499 | H77: 2 000-4 999 | I77: GE | J77: Coopérative agricole | K77: BOULEVARD DE L'ABBAYE 35160 MONTFORT-SUR-MEU | L77: 35160 | M77: MONTFORT-SUR-MEU | N77: 19.8 | O77: 2 | P77: Hors zone (Lamballe-Armor) | Q77: communication@cooperl.com | T77: communication@cooperl.com | U77: https://www.cooperl.com/nous-rejoindre | V77: http://www.cooperl.com | W77: https://www.cooperl.com/mentions-legales | X77: Email de contact général trouvé
A78: GRAND SALOIR SAINT-NICOLAS (LOSTE GRAND SALOIR-LOSTE TRADI-FRANCE-LE DOUESY-GRAND SALOIR SAINT NICOLAS CHARCUTIER) | C78: 709200133 | D78: Préparation industrielle de produits à base de viande | E78: 10.13A | F78: Industrie manufacturière | G78: 250-499 | H78: 500-999 | I78: ETI | J78: SAS | K78: LD LE BIGNON 35137 BEDEE | L78: 35137 | M78: BEDEE | N78: 21.4 | O78: 2 | P78: Hors zone (Paris) | X78: Recherché, aucun site trouvé
A79: CARDIS | B79: E. LECLERC | C79: 378742829 | D79: Hypermarchés | E79: 47.11F | F79: Commerce, réparation auto/moto | G79: 250-499 | H79: 250-499 | I79: ETI | J79: SAS | K79: ZONE ARTISANALE LE CHATEAU GAILLARD 35470 BAIN-DE-BRETAGNE | L79: 35470 | M79: BAIN-DE-BRETAGNE | N79: 28 | O79: 3 | P79: Dans la zone | V79: https://www.e.leclerc/mag/e-leclerc-bain-de-bretagne | X79: Site analysé, aucun email publié
A80: PERRIN SERVICES (BABYCHOU) | C80: 491723789 | D80: Accueil de jeunes enfants | E80: 88.91A | F80: Santé humaine et action sociale | G80: 200-249 | H80: 200-249 | I80: PME | J80: SAS | K80: 17 RUE DE VIARMES 35000 RENNES | L80: 35000 | M80: RENNES | N80: 0.6 | O80: 1 | P80: Dans la zone | Q80: developpement@babychou.com | T80: developpement@babychou.com | U80: https://emploi.babychou.com/ | V80: https://www.babychou.com/ | W80: https://www.babychou.com/ | X80: Email de contact général trouvé
A81: ALLIANZ I.A.R.D. | C81: 542110291 | D81: Autres assurances | E81: 65.12Z | F81: Activités financières et d'assurance | G81: 200-249 | H81: 2 000-4 999 | I81: GE | J81: SA | K81: 20 RUE DU PUITS MAUGER 35000 RENNES | L81: 35000 | M81: RENNES | N81: 0.6 | O81: 1 | P81: Hors zone (Puteaux) | Q81: h935051@agents.allianz.fr | T81: h935051@agents.allianz.fr | U81: https://careers.allianz.com/global/en | V81: https://agence.allianz.fr/ | W81: OpenStreetMap | X81: Email de contact général trouvé
A82: CERCLE PAUL BERT SOC SPORT | C82: 777746702 | D82: Activités de clubs de sports | E82: 93.12Z | F82: Arts, spectacles et activités récréatives | G82: 200-249 | H82: 200-249 | I82: PME | J82: Association | K82: 30 B RUE DE PARIS 35000 RENNES | L82: 35000 | M82: RENNES | N82: 0.9 | O82: 1 | P82: Dans la zone | Q82: cpb@cerclepaulbert.asso.fr | T82: cpb@cerclepaulbert.asso.fr | U82: https://careers.werecruit.io/fr/cercle-paul-bert | V82: https://cerclepaulbert.asso.fr/ | W82: https://cerclepaulbert.asso.fr/contact/ | X82: Email de contact général trouvé
A83: OGEC ST VINCENT-PROVIDENCE | C83: 338896038 | D83: Enseignement secondaire général | E83: 85.31Z | F83: Enseignement | G83: 200-249 | H83: 200-249 | I83: PME | J83: Association | K83: 57 RUE DE PARIS 35000 RENNES | L83: 35000 | M83: RENNES | N83: 1.1 | O83: 1 | P83: Dans la zone | Q83: ce.0350776d@ac-rennes.fr | T83: ce.0350776d@ac-rennes.fr | V83: https://www.saintvincent-rennes.org/ | W83: https://data.education.gouv.fr/explore/dataset/fr-en-annuaire-education/table/?q=0350776D | X83: Email de contact général trouvé
A84: BIOCOOP | C84: 382891752 | D84: Centrales d'achat alimentaires | E84: 46.17A | F84: Commerce, réparation auto/moto | G84: 200-249 | H84: 1 000-1 999 | I84: ETI | J84: SA | K84: 5 RUE DE CHATILLON 35000 RENNES | L84: 35000 | M84: RENNES | N84: 1.1 | O84: 2 | P84: Hors zone (Paris) | U84: https://www.biocoop.fr/nous-rejoindre/recrutement-et-carriere | V84: https://www.biocoop.fr/ | X84: Formulaire / site carrières (pas d'email publié)
A85: ASFAD | C85: 327436531 | D85: Hébergement social pour adultes et familles en difficultés et autre hébergement social | E85: 87.90B | F85: Santé humaine et action sociale | G85: 200-249 | H85: 200-249 | I85: PME | J85: Association | K85: 146 RUE DE LORIENT 35000 RENNES | L85: 35000 | M85: RENNES | N85: 2.6 | O85: 1 | P85: Dans la zone | Q85: siege@asfad.fr | T85: siege@asfad.fr | U85: https://www.asfad.fr/offres-demplois/ | V85: https://www.asfad.fr/ | W85: https://www.asfad.fr/nous-contacter/ | X85: Email de contact général trouvé
A86: SPL EAU DU BASSIN RENNAIS | C86: 798203576 | D86: Captage, traitement et distribution d'eau | E86: 36.00Z | F86: Eau, assainissement, déchets, dépollution | G86: 200-249 | H86: 200-249 | I86: ETI | J86: SA | K86: 15 RUE DOYEN DENIS LEROY 35000 RENNES | L86: 35000 | M86: RENNES | N86: 2.9 | O86: 1 | P86: Dans la zone | V86: https://www.eaudubassinrennais.fr/ | X86: Site analysé, aucun email publié
A87: GROUPE SCOLAIRE D'ENSEIGNEMENT AGRICOLE PRIVE ANTOINE DE SAINT-EXUPERY | C87: 777746199 | D87: Enseignement secondaire technique ou professionnel | E87: 85.32Z | F87: Enseignement | G87: 200-249 | H87: 200-249 | I87: PME | J87: Association | K87: LA LANDE DU BREIL 39 RUE FERNAND ROBERT 35000 RENNES | L87: 35000 | M87: RENNES | N87: 3.2 | O87: 1 | P87: Dans la zone | Q87: lyceesaintexuperyrennes@the-land.bzh | T87: lyceesaintexuperyrennes@the-land.bzh | V87: https://www.groupesaintexupery.fr/ | W87: https://data.education.gouv.fr/explore/dataset/fr-en-annuaire-education/table/?q=0351047Y | X87: Email de contact général trouvé
A88: ALMAREDIS | B88: CARREFOUR | C88: 909401408 | D88: Hypermarchés | E88: 47.11F | F88: Commerce, réparation auto/moto | G88: 200-249 | H88: 200-249 | I88: ETI | J88: SAS | K88: 1 RUE DU BOSPHORE 35200 RENNES | L88: 35200 | M88: RENNES | N88: 3.2 | O88: 1 | P88: Dans la zone | V88: https://www.carrefour.fr/magasin/rennes-centre-alma | X88: Site analysé, aucun email publié
A89: FONDATION SANTE DES ETUDIANTS DE FRANCE (FSEF) | B89: CLINIQUE FSEF RENNES BEAULIEU | C89: 775683006 | D89: Activités hospitalières | E89: 86.10Z | F89: Santé humaine et action sociale | G89: 200-249 | H89: 2 000-4 999 | I89: ETI | J89: Fondation | K89: 41 AVENUE DES BUTTES DE COESMES 35700 RENNES | L89: 35700 | M89: RENNES | N89: 3.4 | O89: 1 | P89: Hors zone (Paris) | U89: https://fsef-sante-etudes.fr/recrutement/ | V89: https://fsef-sante-etudes.fr/ | X89: Formulaire / site carrières (pas d'email publié)
A90: COMPAGNIE ARMORICAINE DE TRANSPORTS (CAT) | B90: TIV | C90: 575450283 | D90: Transports routiers réguliers de voyageurs | E90: 49.39A | F90: Transports et entreposage | G90: 200-249 | H90: 1 000-1 999 | I90: GE | J90: SAS | K90: 20 RUE DU PRE DU BOIS 35000 RENNES | L90: 35000 | M90: RENNES | N90: 3.7 | O90: 1 | P90: Hors zone (Saint-Brieuc) | X90: Pas encore recherché
A91: ADDITI COM (PRECOM) | C91: 348883315 | D91: Régie publicitaire de médias | E91: 73.12Z | F91: Activités spécialisées, scientifiques et techniques | G91: 200-249 | H91: 250-499 | I91: ETI | J91: SAS | K91: 10 RUE DU BREIL 35000 RENNES | L91: 35000 | M91: RENNES | N91: 4.2 | O91: 1 | P91: Dans la zone | V91: http://www.precom.fr | X91: Site analysé, aucun email publié
A92: KEOLIS ARMOR (TAE) | C92: 321840225 | D92: Transports routiers réguliers de voyageurs | E92: 49.39A | F92: Transports et entreposage | G92: 200-249 | H92: 250-499 | I92: GE | J92: SAS | K92: ZI CHANTEPIE 26 RUE DU BIGNON 35135 CHANTEPIE | L92: 35135 | M92: CHANTEPIE | N92: 4.3 | O92: 2 | P92: Dans la zone | V92: https://keolis-armor.com/ | X92: Site analysé, aucun email publié
A93: LEROY MERLIN FRANCE | C93: 384560942 | D93: Commerce de détail de quincaillerie, peintures et verres en grandes surfaces (400 m2et plus) | E93: 47.52B | F93: Commerce, réparation auto/moto | G93: 200-249 | H93: 10 000 et + | I93: GE | J93: SA | K93: PARC D'ACTIVITE ROCADE SUD 16 ALLEE DE GUERLEDAN 35135 CHANTEPIE | L93: 35135 | M93: CHANTEPIE | N93: 4.5 | O93: 1 | P93: Hors zone (Lezennes) | V93: https://www.leroymerlin.fr/magasins/chantepie-rennes-sud.html | X93: Site analysé, aucun email publié
A94: CAISSE D'EPARGNE ET DE PREVOYANCE BRETAGNE - PAYS DE LOIRE (CEBPL) | C94: 392640090 | D94: Autres intermédiations monétaires | E94: 64.19Z | F94: Activités financières et d'assurance | G94: 200-249 | H94: 2 000-4 999 | I94: GE | J94: Société coopérative / bancaire | K94: RDC 4 A RUE DU CHENE GERMAIN 35510 CESSON-SEVIGNE | L94: 35510 | M94: CESSON-SEVIGNE | N94: 4.5 | O94: 3 | P94: Hors zone (Nantes) | V94: https://www.agences.caisse-epargne.fr/banque-assurance/chateaugiron-id14445022229 | X94: Site analysé, aucun email publié
A95: EIFFAGE ENERGIE SYSTEMES - CLEMESSY (EES - CLEMESSY) | C95: 945752137 | D95: Travaux d'installation électrique dans tous locaux | E95: 43.21A | F95: Construction | G95: 200-249 | H95: 2 000-4 999 | I95: GE | J95: SA | K95: FORUM DE LA ROCADE 38 RUE DU BIGNON 35510 CESSON-SEVIGNE | L95: 35510 | M95: CESSON-SEVIGNE | N95: 4.8 | O95: 1 | P95: Hors zone (Mulhouse) | Q95: cy.rennes@clemessy.fr | T95: cy.rennes@clemessy.fr | U95: https://www.clemessy.com/recrutement | V95: https://www.clemessy.com/ | W95: Overture Maps (données ouvertes, fiche lieu « Clemessy ») | X95: Email de contact général trouvé
A96: SAMSIC SECURITE | C96: 440319101 | D96: Activités de sécurité privée | E96: 80.10Z | F96: Services administratifs et de soutien | G96: 200-249 | H96: 2 000-4 999 | I96: GE | J96: SAS | K96: FORUM DE LA ROCADE 40 RUE DU BIGNON 35510 CESSON-SEVIGNE | L96: 35510 | M96: CESSON-SEVIGNE | N96: 5 | O96: 1 | P96: Hors zone (Saint-Denis) | Q96: contact@samsic-facility.fr | T96: contact@samsic-facility.fr | U96: https://www.samsic-emploi.fr/ | W96: https://www.samsic.fr/mentions-legales/ | X96: Email de contact général trouvé
A97: SOLOCAL (PAGES BLANCHES - PAGES JAUNES - RENSEIGNEMENTS TELEPHONIQUES PAGESJAUNES) | C97: 444212955 | D97: Édition de répertoires et de fichiers d'adresses | E97: 58.12Z | F97: Information et communication | G97: 200-249 | H97: 1 000-1 999 | I97: ETI | J97: SA | K97: IMMEUBLE ATRIUM BATIMENT B & C 2 RUE CLAUDE CHAPPE 35510 CESSON-SEVIGNE | L97: 35510 | M97: CESSON-SEVIGNE | N97: 5.1 | O97: 1 | P97: Hors zone (Boulogne-Billancourt) | U97: https://recrutement.solocal.com/ | V97: https://www.solocal.com | X97: Formulaire / site carrières (pas d'email publié)
A98: ALTRAN TECHNOLOGIES | C98: 702012956 | D98: Ingénierie, études techniques | E98: 71.12B | F98: Information et communication | G98: 200-249 | H98: 5 000-9 999 | I98: GE | J98: SAS | K98: 7 RUE CLAUDE CHAPPE 35510 CESSON-SEVIGNE | L98: 35510 | M98: CESSON-SEVIGNE | N98: 5.1 | O98: 1 | P98: Hors zone (Paris) | V98: http://www.altran.com | X98: Site analysé, aucun email publié
A99: TALENDI | C99: 304602527 | D99: Fabrication d'autres équipements automobiles | E99: 29.32Z | F99: Industrie manufacturière | G99: 200-249 | H99: 250-499 | I99: ETI | J99: Association | K99: ZA TOUCHE TIZON RUE DU COMTE DE DION 35230 NOYAL-CHATILLON-SUR-SEICHE | L99: 35230 | M99: NOYAL-CHATILLON-SUR-SEICHE | N99: 6.5 | O99: 4 | P99: Dans la zone | Q99: contact@talendi.com | T99: contact@talendi.com | U99: https://www.talendi.com/emploi/rejoignez-nous/ | V99: https://www.talendi.com/ | W99: https://www.ville-noyal-chatillon.fr/guide-pratique/bretagne-ateliers/ | X99: Email de contact général trouvé
A100: HEXAGONE | C100: 502317332 | D100: Activités des sociétés holding | E100: 64.20Z | F100: Activités financières et d'assurance | G100: 200-249 | H100: 200-249 | I100: GE | J100: SAS | K100: PARC TERTIAIRE DU VAL D ORSON RUE DU PRE LONG 35770 VERN-SUR-SEICHE | L100: 35770 | M100: VERN-SUR-SEICHE | N100: 6.6 | O100: 1 | P100: Dans la zone | X100: Pas encore recherché
...

Sheet Synthèse
A1: Entreprises de 10 salariés et plus à moins de 30 km de Rennes
A3: Indicateur | B3: Nombre
A4: Entreprises listées | B4: =COUNTA(Entreprises!$C$2:$C$4332) -> 4331
A5: Avec un email pour candidater | B5: =COUNTIF(Entreprises!$Q$2:$Q$4332,"?*") -> 1966
A6: dont email RH / recrutement | B6: =COUNTIF(Entreprises!$R$2:$R$4332,"?*") -> 88
A7: dont email SI / informatique | B7: =COUNTIF(Entreprises!$S$2:$S$4332,"?*") -> 1
A8: Avec un email de contact général | B8: =COUNTIF(Entreprises!$T$2:$T$4332,"?*") -> 1925
A9: Avec une page carrières / candidature | B9: =COUNTIF(Entreprises!$U$2:$U$4332,"?*") -> 783
A10: Avec un site web identifié | B10: =COUNTIF(Entreprises!$V$2:$V$4332,"?*") -> 1803
A12: Statut de la recherche
A13: Email RH / recrutement trouvé | B13: =COUNTIF(Entreprises!$X$2:$X$4332,A13) -> 88
A14: Email SI / informatique trouvé | B14: =COUNTIF(Entreprises!$X$2:$X$4332,A14) -> 1
A15: Email de contact général trouvé | B15: =COUNTIF(Entreprises!$X$2:$X$4332,A15) -> 1877
A16: Formulaire / site carrières (pas d'email publié) | B16: =COUNTIF(Entreprises!$X$2:$X$4332,A16) -> 147
A17: Site analysé, aucun email publié | B17: =COUNTIF(Entreprises!$X$2:$X$4332,A17) -> 231
A18: Recherché, aucun site trouvé | B18: =COUNTIF(Entreprises!$X$2:$X$4332,A18) -> 156
A19: Site trouvé, pas encore analysé | B19: =COUNTIF(Entreprises!$X$2:$X$4332,A19) -> 102
A20: Pas encore recherché | B20: =COUNTIF(Entreprises!$X$2:$X$4332,A20) -> 1653
A22: Effectif local (tranche INSEE) | B22: Entreprises | C22: dont avec email
A23: 10-19 | B23: =COUNTIF(Entreprises!$G$2:$G$4332,A23)+COUNTIF(Entreprises!$G$2:$G$4332,A23&" (estim.)") -> 2119 | C23: =COUNTIFS(Entreprises!$G$2:$G$4332,A23,Entreprises!$Q$2:$Q$4332,"?*")+COUNTIFS(Entreprises!$G$2:$G$4332,A23&" (estim.)",Entreprises!$Q$2:$Q$4332,"?*") -> 852
A24: 20-49 | B24: =COUNTIF(Entreprises!$G$2:$G$4332,A24)+COUNTIF(Entreprises!$G$2:$G$4332,A24&" (estim.)") -> 1394 | C24: =COUNTIFS(Entreprises!$G$2:$G$4332,A24,Entreprises!$Q$2:$Q$4332,"?*")+COUNTIFS(Entreprises!$G$2:$G$4332,A24&" (estim.)",Entreprises!$Q$2:$Q$4332,"?*") -> 686
A25: 50-99 | B25: =COUNTIF(Entreprises!$G$2:$G$4332,A25)+COUNTIF(Entreprises!$G$2:$G$4332,A25&" (estim.)") -> 491 | C25: =COUNTIFS(Entreprises!$G$2:$G$4332,A25,Entreprises!$Q$2:$Q$4332,"?*")+COUNTIFS(Entreprises!$G$2:$G$4332,A25&" (estim.)",Entreprises!$Q$2:$Q$4332,"?*") -> 277
A26: 100-199 | B26: =COUNTIF(Entreprises!$G$2:$G$4332,A26)+COUNTIF(Entreprises!$G$2:$G$4332,A26&" (estim.)") -> 212 | C26: =COUNTIFS(Entreprises!$G$2:$G$4332,A26,Entreprises!$Q$2:$Q$4332,"?*")+COUNTIFS(Entreprises!$G$2:$G$4332,A26&" (estim.)",Entreprises!$Q$2:$Q$4332,"?*") -> 102
A27: 200-249 | B27: =COUNTIF(Entreprises!$G$2:$G$4332,A27)+COUNTIF(Entreprises!$G$2:$G$4332,A27&" (estim.)") -> 37 | C27: =COUNTIFS(Entreprises!$G$2:$G$4332,A27,Entreprises!$Q$2:$Q$4332,"?*")+COUNTIFS(Entreprises!$G$2:$G$4332,A27&" (estim.)",Entreprises!$Q$2:$Q$4332,"?*") -> 16
A28: 250-499 | B28: =COUNTIF(Entreprises!$G$2:$G$4332,A28)+COUNTIF(Entreprises!$G$2:$G$4332,A28&" (estim.)") -> 57 | C28: =COUNTIFS(Entreprises!$G$2:$G$4332,A28,Entreprises!$Q$2:$Q$4332,"?*")+COUNTIFS(Entreprises!$G$2:$G$4332,A28&" (estim.)",Entreprises!$Q$2:$Q$4332,"?*") -> 23
A29: 500-999 | B29: =COUNTIF(Entreprises!$G$2:$G$4332,A29)+COUNTIF(Entreprises!$G$2:$G$4332,A29&" (estim.)") -> 15 | C29: =COUNTIFS(Entreprises!$G$2:$G$4332,A29,Entreprises!$Q$2:$Q$4332,"?*")+COUNTIFS(Entreprises!$G$2:$G$4332,A29&" (estim.)",Entreprises!$Q$2:$Q$4332,"?*") -> 10
A30: 1 000-1 999 | B30: =COUNTIF(Entreprises!$G$2:$G$4332,A30)+COUNTIF(Entreprises!$G$2:$G$4332,A30&" (estim.)") -> 6 | C30: =COUNTIFS(Entreprises!$G$2:$G$4332,A30,Entreprises!$Q$2:$Q$4332,"?*")+COUNTIFS(Entreprises!$G$2:$G$4332,A30&" (estim.)",Entreprises!$Q$2:$Q$4332,"?*") -> 0
A32: Secteur | B32: Entreprises | C32: dont avec email
A33: Activités financières et d'assurance | B33: =COUNTIF(Entreprises!$F$2:$F$4332,A33) -> 127 | C33: =COUNTIFS(Entreprises!$F$2:$F$4332,A33,Entreprises!$Q$2:$Q$4332,"?*") -> 35
A34: Activités immobilières | B34: =COUNTIF(Entreprises!$F$2:$F$4332,A34) -> 55 | C34: =COUNTIFS(Entreprises!$F$2:$F$4332,A34,Entreprises!$Q$2:$Q$4332,"?*") -> 30
A35: Activités spécialisées, scientifiques et techniques | B35: =COUNTIF(Entreprises!$F$2:$F$4332,A35) -> 474 | C35: =COUNTIFS(Entreprises!$F$2:$F$4332,A35,Entreprises!$Q$2:$Q$4332,"?*") -> 206
A36: Administration publique | B36: =COUNTIF(Entreprises!$F$2:$F$4332,A36) -> 17 | C36: =COUNTIFS(Entreprises!$F$2:$F$4332,A36,Entreprises!$Q$2:$Q$4332,"?*") -> 8
A37: Agriculture, sylviculture et pêche | B37: =COUNTIF(Entreprises!$F$2:$F$4332,A37) -> 43 | C37: =COUNTIFS(Entreprises!$F$2:$F$4332,A37,Entreprises!$Q$2:$Q$4332,"?*") -> 13
A38: Arts, spectacles et activités récréatives | B38: =COUNTIF(Entreprises!$F$2:$F$4332,A38) -> 99 | C38: =COUNTIFS(Entreprises!$F$2:$F$4332,A38,Entreprises!$Q$2:$Q$4332,"?*") -> 68
A39: Autres activités de services | B39: =COUNTIF(Entreprises!$F$2:$F$4332,A39) -> 145 | C39: =COUNTIFS(Entreprises!$F$2:$F$4332,A39,Entreprises!$Q$2:$Q$4332,"?*") -> 84
A40: Commerce, réparation auto/moto | B40: =COUNTIF(Entreprises!$F$2:$F$4332,A40) -> 749 | C40: =COUNTIFS(Entreprises!$F$2:$F$4332,A40,Entreprises!$Q$2:$Q$4332,"?*") -> 285
A41: Construction | B41: =COUNTIF(Entreprises!$F$2:$F$4332,A41) -> 478 | C41: =COUNTIFS(Entreprises!$F$2:$F$4332,A41,Entreprises!$Q$2:$Q$4332,"?*") -> 231
A42: Eau, assainissement, déchets, dépollution | B42: =COUNTIF(Entreprises!$F$2:$F$4332,A42) -> 26 | C42: =COUNTIFS(Entreprises!$F$2:$F$4332,A42,Entreprises!$Q$2:$Q$4332,"?*") -> 9
A43: Enseignement | B43: =COUNTIF(Entreprises!$F$2:$F$4332,A43) -> 236 | C43: =COUNTIFS(Entreprises!$F$2:$F$4332,A43,Entreprises!$Q$2:$Q$4332,"?*") -> 207
A44: Hébergement et restauration | B44: =COUNTIF(Entreprises!$F$2:$F$4332,A44) -> 374 | C44: =COUNTIFS(Entreprises!$F$2:$F$4332,A44,Entreprises!$Q$2:$Q$4332,"?*") -> 175
... A51: Énergie (électricité, gaz, vapeur) | B51: =COUNTIF(Entreprises!$F$2:$F$4332,A51) -> 10 | C51: =COUNTIFS(Entreprises!$F$2:$F$4332,A51,Entreprises!$Q$2:$Q$4332,"?*") -> 1

Sheet Méthode et limites
A1: Méthode et limites
A3: Périmètre
A4: Établissements actifs situés à 30 km ou moins de l'hôtel de ville de Rennes, comptant au moins 10 salariés sur place (tranche d'effectif INSEE de l'établissement). Une ligne par entreprise (SIREN) ; l'adresse affichée est celle de son plus gros établissement dans la zone. Quand l'effectif local n'est pas renseigné pour une entreprise mono-site, l'effectif de l'entreprise est repris, signalé « (estim.) ».
A5: Tous secteurs privés, associations et entreprises publiques (EPIC) compris. Administrations, collectivités et établissements publics administratifs exclus (secteur public non retenu).
A7: Sources
A8: Liste des entreprises : base SIRENE (INSEE) via l'API Recherche d'entreprises de l'État, extraction du 18/10/2026. Licence Ouverte Etalab.
A9: Sites web et emails : sites officiels des entreprises (pages accueil, contact, recrutement, mentions légales), liste des entreprises RGE de l'ADEME (Licence Ouverte), Wikidata (CC0) et OpenStreetMap (© contributeurs OpenStreetMap, licence ODbL).
A10: Annuaires officiels utilisés en complément : annuaire de l'Éducation nationale (data.education.gouv.fr, Licence Ouverte) pour les écoles privées (OGEC), Annuaire social du Département d'Ille-et-Vilaine, annuaires des communes (Pacé, Noyal-Châtillon-sur-Seiche, Chartres-de-Bretagne, Châteaubourg, L'Hermitage, Guichen, Louvigné-de-Bais…), annuaire de la CRESS Bretagne, Chambre des notaires, et DATAtourisme (sites web des restaurants et hôtels).
A11: Ajouts récents : référentiel « Sites et organismes » de Rennes Métropole (data.rennesmetropole.fr), jeux de données ouverts de la Région Bretagne (data.bretagne.bzh), Plateforme de l'inclusion (structures d'insertion), annuaire OPQIBI (ingénierie), annuaires des membres du Poool (French Tech Rennes) et de Produit en Bretagne (sites web), annuaires de La Mézière, Vern-sur-Seiche, Saint-Gilles, Bréal-sous-Montfort, Melesse, Liffré-Cormier, Servon, annuaire des organismes de formation du GREF Bretagne. Pour quelques filiales de groupes installées au siège du groupe (Samsic, Legendre), l'adresse est celle du groupe.
A12: Données Overture Maps Foundation (lieux, édition 2026-09, licences CDLA-Permissive / ODbL) : adresses et sites publiés sur les fiches publiques des établissements, rapprochées par nom et position GPS (moins de 300 m en général) puis vérifiées une à une ; la colonne « Source des emails » cite la fiche utilisée. Quand l'adresse trouvée est celle du groupe ou de l'enseigne (ex. magasin d'une chaîne), la note « groupe » est indiquée.
A13: La colonne « Source des emails » indique la page ou le jeu de données d'où proviennent les adresses.
A15: Colonnes de contact
... A25: Pour des candidatures, privilégie des messages individuels et personnalisés plutôt qu'un envoi groupé, qui finit souvent en spam.
